django_thummer-3.0.dev1.dist-info/DESCRIPTION.rst
django_thummer-3.0.dev1.dist-info/LICENSE.txt
django_thummer-3.0.dev1.dist-info/METADATA
django_thummer-3.0.dev1.dist-info/RECORD
django_thummer-3.0.dev1.dist-info/WHEEL
django_thummer-3.0.dev1.dist-info/metadata.json
django_thummer-3.0.dev1.dist-info/top_level.txt
thummer/__init__.py
thummer/admin.py
thummer/apps.py
thummer/models.py
thummer/querysets.py
thummer/receivers.py
thummer/settings.py
thummer/tasks.py
thummer/urls.py
thummer/utils.py
thummer/views.py
thummer/migrations/0001_initial.py
thummer/migrations/0002_auto_20180208_2312.py
thummer/migrations/0003_auto_20180209_1412.py
thummer/migrations/__init__.py
thummer/templatetags/__init__.py
thummer/templatetags/thummer.py
thummer/tests/__init__.py
thummer/tests/test_models.py
thummer/tests/test_thing.py
