Metadata-Version: 2.0
Name: django-thummer
Version: 3.0.dev1
Summary: A website screenshot and thumbnailing app for Django.
Home-page: https://github.com/mattaustin/django-thummer
Author: Matt Austin
Author-email: devops@mattaustin.com.au
License: Apache 2.0
Keywords: thummer django website snapshot screenshot thumbnail
Platform: UNKNOWN
Classifier: Development Status :: 3 - Alpha
Classifier: Environment :: Web Environment
Classifier: Framework :: Django
Classifier: Framework :: Django :: 1.8
Classifier: Framework :: Django :: 1.11
Classifier: Framework :: Django :: 2.0
Classifier: Intended Audience :: Developers
Classifier: License :: OSI Approved :: Apache Software License
Classifier: Operating System :: OS Independent
Classifier: Programming Language :: Python
Classifier: Programming Language :: Python :: 2.7
Classifier: Programming Language :: Python :: 3.4
Classifier: Programming Language :: Python :: 3.5
Classifier: Programming Language :: Python :: 3.6
Classifier: Topic :: Internet :: WWW/HTTP :: Dynamic Content
Classifier: Topic :: Multimedia :: Graphics :: Capture
Requires-Python: >=2.7, !=3.0.*, !=3.1.*, !=3.2.*, !=3.3.*, <4
Requires-Dist: django (!=1.10.*,!=1.9.*,<=2.1,>=1.8)
Requires-Dist: pillow (~=5.0)
Requires-Dist: python-dateutil (~=2.6)
Requires-Dist: selenium (~=3.9)
Requires-Dist: sorl-thumbnail (~=12.4)
Provides-Extra: tests
Requires-Dist: coverage (~=4.5); extra == 'tests'
Requires-Dist: freezegun (~=0.3); extra == 'tests'
Requires-Dist: mock (~=2.0); extra == 'tests'
Requires-Dist: pytz; extra == 'tests'
